[
  {
    "ContainingType": "WebApiCrud.Controllers.EmpeadoController",
    "Method": "Editar",
    "RelativePath": "api/Empeado/Editar",
    "HttpMethod": "PUT",
    "IsController": true,
    "Order": 0,
    "Parameters": [
      {
        "Name": "objeto",
        "Type": "WebApiCrud.Models.Empleado",
        "IsRequired": true
      }
    ],
    "ReturnTypes": []
  },
  {
    "ContainingType": "WebApiCrud.Controllers.EmpeadoController",
    "Method": "Eliminar",
    "RelativePath": "api/Empeado/Eliminar/{id}",
    "HttpMethod": "DELETE",
    "IsController": true,
    "Order": 0,
    "Parameters": [
      {
        "Name": "id",
        "Type": "System.Int32",
        "IsRequired": true
      }
    ],
    "ReturnTypes": []
  },
  {
    "ContainingType": "WebApiCrud.Controllers.EmpeadoController",
    "Method": "Get",
    "RelativePath": "api/Empeado/Lista",
    "HttpMethod": "GET",
    "IsController": true,
    "Order": 0,
    "Parameters": [],
    "ReturnTypes": []
  },
  {
    "ContainingType": "WebApiCrud.Controllers.EmpeadoController",
    "Method": "Nuevo",
    "RelativePath": "api/Empeado/Nuevo",
    "HttpMethod": "POST",
    "IsController": true,
    "Order": 0,
    "Parameters": [
      {
        "Name": "objeto",
        "Type": "WebApiCrud.Models.Empleado",
        "IsRequired": true
      }
    ],
    "ReturnTypes": []
  },
  {
    "ContainingType": "WebApiCrud.Controllers.EmpeadoController",
    "Method": "Get",
    "RelativePath": "api/Empeado/Obtener/{id}",
    "HttpMethod": "GET",
    "IsController": true,
    "Order": 0,
    "Parameters": [
      {
        "Name": "id",
        "Type": "System.Int32",
        "IsRequired": true
      }
    ],
    "ReturnTypes": []
  },
  {
    "ContainingType": "WebApiCrud.Controllers.WeatherForecastController",
    "Method": "Get",
    "RelativePath": "WeatherForecast",
    "HttpMethod": "GET",
    "IsController": true,
    "Order": 0,
    "Parameters": [],
    "ReturnTypes": [
      {
        "Type": "System.Collections.Generic.IEnumerable\u00601[[WebApiCrud.WeatherForecast, WebApiCrud, Version=1.0.0.0, Culture=neutral, PublicKeyToken=null]]",
        "MediaTypes": [
          "text/plain",
          "application/json",
          "text/json"
        ],
        "StatusCode": 200
      }
    ],
    "EndpointName": "GetWeatherForecast"
  }
]